{
  "version": "6",
  "dialect": "sqlite",
  "id": "9a643efd-f6d9-4b1d-87eb-1a3ec6aa1bf8",
  "prevId": "7261972a-1b00-4323-b570-9f252e91dd80",
  "tables": {
    "attempts": {
      "name": "attempts",
      "columns": {
        "id": {
          "name": "id",
          "type": "text",
          "primaryKey": true,
          "notNull": true,
          "autoincrement": false
        },
        "chat_id": {
          "name": "chat_id",
          "type": "text",
          "primaryKey": false,
          "notNull": true,
          "autoincrement": false
        },
        "codex_thread_id": {
          "name": "codex_thread_id",
          "type": "text",
          "primaryKey": false,
          "notNull": false,
          "autoincrement": false
        },
        "status": {
          "name": "status",
          "type": "text",
          "primaryKey": false,
          "notNull": true,
          "autoincrement": false,
          "default": "'running'"
        },
        "result": {
          "name": "result",
          "type": "text",
          "primaryKey": false,
          "notNull": false,
          "autoincrement": false
        },
        "error": {
          "name": "error",
          "type": "text",
          "primaryKey": false,
          "notNull": false,
          "autoincrement": false
        },
        "created_at": {
          "name": "created_at",
          "type": "integer",
          "primaryKey": false,
          "notNull": true,
          "autoincrement": false
        }
      },
      "indexes": {
        "idx_attempts_chat_id": {
          "name": "idx_attempts_chat_id",
          "columns": ["chat_id"],
          "isUnique": false
        },
        "idx_attempts_status": {
          "name": "idx_attempts_status",
          "columns": ["status"],
          "isUnique": false
        }
      },
      "foreignKeys": {
        "attempts_chat_id_chats_id_fk": {
          "name": "attempts_chat_id_chats_id_fk",
          "tableFrom": "attempts",
          "tableTo": "chats",
          "columnsFrom": ["chat_id"],
          "columnsTo": ["id"],
          "onDelete": "cascade",
          "onUpdate": "no action"
        }
      },
      "compositePrimaryKeys": {},
      "uniqueConstraints": {},
      "checkConstraints": {}
    },
    "chats": {
      "name": "chats",
      "columns": {
        "id": {
          "name": "id",
          "type": "text",
          "primaryKey": true,
          "notNull": true,
          "autoincrement": false
        },
        "workspace_id": {
          "name": "workspace_id",
          "type": "text",
          "primaryKey": false,
          "notNull": true,
          "autoincrement": false
        },
        "codex_thread_id": {
          "name": "codex_thread_id",
          "type": "text",
          "primaryKey": false,
          "notNull": false,
          "autoincrement": false
        },
        "title": {
          "name": "title",
          "type": "text",
          "primaryKey": false,
          "notNull": false,
          "autoincrement": false
        },
        "status": {
          "name": "status",
          "type": "text",
          "primaryKey": false,
          "notNull": true,
          "autoincrement": false,
          "default": "'active'"
        },
        "created_at": {
          "name": "created_at",
          "type": "integer",
          "primaryKey": false,
          "notNull": true,
          "autoincrement": false
        },
        "updated_at": {
          "name": "updated_at",
          "type": "integer",
          "primaryKey": false,
          "notNull": true,
          "autoincrement": false
        }
      },
      "indexes": {
        "idx_chats_workspace_id": {
          "name": "idx_chats_workspace_id",
          "columns": ["workspace_id"],
          "isUnique": false
        },
        "idx_chats_status": {
          "name": "idx_chats_status",
          "columns": ["status"],
          "isUnique": false
        },
        "idx_chats_updated_at": {
          "name": "idx_chats_updated_at",
          "columns": ["updated_at"],
          "isUnique": false
        }
      },
      "foreignKeys": {
        "chats_workspace_id_workspaces_id_fk": {
          "name": "chats_workspace_id_workspaces_id_fk",
          "tableFrom": "chats",
          "tableTo": "workspaces",
          "columnsFrom": ["workspace_id"],
          "columnsTo": ["id"],
          "onDelete": "cascade",
          "onUpdate": "no action"
        }
      },
      "compositePrimaryKeys": {},
      "uniqueConstraints": {},
      "checkConstraints": {}
    },
    "plans": {
      "name": "plans",
      "columns": {
        "id": {
          "name": "id",
          "type": "text",
          "primaryKey": true,
          "notNull": true,
          "autoincrement": false
        },
        "project_id": {
          "name": "project_id",
          "type": "text",
          "primaryKey": false,
          "notNull": true,
          "autoincrement": false
        },
        "chat_id": {
          "name": "chat_id",
          "type": "text",
          "primaryKey": false,
          "notNull": true,
          "autoincrement": false
        },
        "agent_id": {
          "name": "agent_id",
          "type": "text",
          "primaryKey": false,
          "notNull": true,
          "autoincrement": false
        },
        "title": {
          "name": "title",
          "type": "text",
          "primaryKey": false,
          "notNull": true,
          "autoincrement": false
        },
        "content": {
          "name": "content",
          "type": "text",
          "primaryKey": false,
          "notNull": true,
          "autoincrement": false
        },
        "status": {
          "name": "status",
          "type": "text",
          "primaryKey": false,
          "notNull": true,
          "autoincrement": false,
          "default": "'pending'"
        },
        "feedback": {
          "name": "feedback",
          "type": "text",
          "primaryKey": false,
          "notNull": false,
          "autoincrement": false
        },
        "created_at": {
          "name": "created_at",
          "type": "integer",
          "primaryKey": false,
          "notNull": true,
          "autoincrement": false
        },
        "responded_at": {
          "name": "responded_at",
          "type": "integer",
          "primaryKey": false,
          "notNull": false,
          "autoincrement": false
        }
      },
      "indexes": {
        "idx_plans_project_id": {
          "name": "idx_plans_project_id",
          "columns": ["project_id"],
          "isUnique": false
        },
        "idx_plans_chat_id": {
          "name": "idx_plans_chat_id",
          "columns": ["chat_id"],
          "isUnique": false
        },
        "idx_plans_status": {
          "name": "idx_plans_status",
          "columns": ["status"],
          "isUnique": false
        },
        "idx_plans_chat_status": {
          "name": "idx_plans_chat_status",
          "columns": ["chat_id", "status"],
          "isUnique": false
        }
      },
      "foreignKeys": {
        "plans_project_id_projects_id_fk": {
          "name": "plans_project_id_projects_id_fk",
          "tableFrom": "plans",
          "tableTo": "projects",
          "columnsFrom": ["project_id"],
          "columnsTo": ["id"],
          "onDelete": "cascade",
          "onUpdate": "no action"
        },
        "plans_chat_id_chats_id_fk": {
          "name": "plans_chat_id_chats_id_fk",
          "tableFrom": "plans",
          "tableTo": "chats",
          "columnsFrom": ["chat_id"],
          "columnsTo": ["id"],
          "onDelete": "cascade",
          "onUpdate": "no action"
        }
      },
      "compositePrimaryKeys": {},
      "uniqueConstraints": {},
      "checkConstraints": {}
    },
    "projects": {
      "name": "projects",
      "columns": {
        "id": {
          "name": "id",
          "type": "text",
          "primaryKey": true,
          "notNull": true,
          "autoincrement": false
        },
        "path": {
          "name": "path",
          "type": "text",
          "primaryKey": false,
          "notNull": true,
          "autoincrement": false
        },
        "name": {
          "name": "name",
          "type": "text",
          "primaryKey": false,
          "notNull": true,
          "autoincrement": false
        },
        "default_branch": {
          "name": "default_branch",
          "type": "text",
          "primaryKey": false,
          "notNull": true,
          "autoincrement": false
        },
        "created_at": {
          "name": "created_at",
          "type": "integer",
          "primaryKey": false,
          "notNull": true,
          "autoincrement": false
        }
      },
      "indexes": {
        "projects_path_unique": {
          "name": "projects_path_unique",
          "columns": ["path"],
          "isUnique": true
        },
        "idx_projects_created_at": {
          "name": "idx_projects_created_at",
          "columns": ["created_at"],
          "isUnique": false
        }
      },
      "foreignKeys": {},
      "compositePrimaryKeys": {},
      "uniqueConstraints": {},
      "checkConstraints": {}
    },
    "questions": {
      "name": "questions",
      "columns": {
        "id": {
          "name": "id",
          "type": "text",
          "primaryKey": true,
          "notNull": true,
          "autoincrement": false
        },
        "chat_id": {
          "name": "chat_id",
          "type": "text",
          "primaryKey": false,
          "notNull": true,
          "autoincrement": false
        },
        "agent_id": {
          "name": "agent_id",
          "type": "text",
          "primaryKey": false,
          "notNull": true,
          "autoincrement": false
        },
        "content": {
          "name": "content",
          "type": "text",
          "primaryKey": false,
          "notNull": true,
          "autoincrement": false
        },
        "status": {
          "name": "status",
          "type": "text",
          "primaryKey": false,
          "notNull": true,
          "autoincrement": false,
          "default": "'pending'"
        },
        "answer": {
          "name": "answer",
          "type": "text",
          "primaryKey": false,
          "notNull": false,
          "autoincrement": false
        },
        "created_at": {
          "name": "created_at",
          "type": "integer",
          "primaryKey": false,
          "notNull": true,
          "autoincrement": false
        },
        "responded_at": {
          "name": "responded_at",
          "type": "integer",
          "primaryKey": false,
          "notNull": false,
          "autoincrement": false
        }
      },
      "indexes": {
        "idx_questions_chat_id": {
          "name": "idx_questions_chat_id",
          "columns": ["chat_id"],
          "isUnique": false
        },
        "idx_questions_status": {
          "name": "idx_questions_status",
          "columns": ["status"],
          "isUnique": false
        },
        "idx_questions_chat_status": {
          "name": "idx_questions_chat_status",
          "columns": ["chat_id", "status"],
          "isUnique": false
        }
      },
      "foreignKeys": {
        "questions_chat_id_chats_id_fk": {
          "name": "questions_chat_id_chats_id_fk",
          "tableFrom": "questions",
          "tableTo": "chats",
          "columnsFrom": ["chat_id"],
          "columnsTo": ["id"],
          "onDelete": "cascade",
          "onUpdate": "no action"
        }
      },
      "compositePrimaryKeys": {},
      "uniqueConstraints": {},
      "checkConstraints": {}
    },
    "subagents": {
      "name": "subagents",
      "columns": {
        "id": {
          "name": "id",
          "type": "text",
          "primaryKey": true,
          "notNull": true,
          "autoincrement": false
        },
        "parent_chat_id": {
          "name": "parent_chat_id",
          "type": "text",
          "primaryKey": false,
          "notNull": true,
          "autoincrement": false
        },
        "parent_attempt_id": {
          "name": "parent_attempt_id",
          "type": "text",
          "primaryKey": false,
          "notNull": false,
          "autoincrement": false
        },
        "task": {
          "name": "task",
          "type": "text",
          "primaryKey": false,
          "notNull": true,
          "autoincrement": false
        },
        "status": {
          "name": "status",
          "type": "text",
          "primaryKey": false,
          "notNull": true,
          "autoincrement": false,
          "default": "'running'"
        },
        "result": {
          "name": "result",
          "type": "text",
          "primaryKey": false,
          "notNull": false,
          "autoincrement": false
        },
        "error": {
          "name": "error",
          "type": "text",
          "primaryKey": false,
          "notNull": false,
          "autoincrement": false
        },
        "created_at": {
          "name": "created_at",
          "type": "integer",
          "primaryKey": false,
          "notNull": true,
          "autoincrement": false
        }
      },
      "indexes": {
        "idx_subagents_parent_chat_id": {
          "name": "idx_subagents_parent_chat_id",
          "columns": ["parent_chat_id"],
          "isUnique": false
        },
        "idx_subagents_parent_attempt_id": {
          "name": "idx_subagents_parent_attempt_id",
          "columns": ["parent_attempt_id"],
          "isUnique": false
        },
        "idx_subagents_status": {
          "name": "idx_subagents_status",
          "columns": ["status"],
          "isUnique": false
        }
      },
      "foreignKeys": {
        "subagents_parent_chat_id_chats_id_fk": {
          "name": "subagents_parent_chat_id_chats_id_fk",
          "tableFrom": "subagents",
          "tableTo": "chats",
          "columnsFrom": ["parent_chat_id"],
          "columnsTo": ["id"],
          "onDelete": "cascade",
          "onUpdate": "no action"
        },
        "subagents_parent_attempt_id_attempts_id_fk": {
          "name": "subagents_parent_attempt_id_attempts_id_fk",
          "tableFrom": "subagents",
          "tableTo": "attempts",
          "columnsFrom": ["parent_attempt_id"],
          "columnsTo": ["id"],
          "onDelete": "set null",
          "onUpdate": "no action"
        }
      },
      "compositePrimaryKeys": {},
      "uniqueConstraints": {},
      "checkConstraints": {}
    },
    "tasks": {
      "name": "tasks",
      "columns": {
        "id": {
          "name": "id",
          "type": "text",
          "primaryKey": true,
          "notNull": true,
          "autoincrement": false
        },
        "chat_id": {
          "name": "chat_id",
          "type": "text",
          "primaryKey": false,
          "notNull": true,
          "autoincrement": false
        },
        "description": {
          "name": "description",
          "type": "text",
          "primaryKey": false,
          "notNull": true,
          "autoincrement": false
        },
        "claimed_by": {
          "name": "claimed_by",
          "type": "text",
          "primaryKey": false,
          "notNull": false,
          "autoincrement": false
        },
        "status": {
          "name": "status",
          "type": "text",
          "primaryKey": false,
          "notNull": true,
          "autoincrement": false,
          "default": "'pending'"
        },
        "result": {
          "name": "result",
          "type": "text",
          "primaryKey": false,
          "notNull": false,
          "autoincrement": false
        },
        "created_at": {
          "name": "created_at",
          "type": "integer",
          "primaryKey": false,
          "notNull": true,
          "autoincrement": false
        },
        "updated_at": {
          "name": "updated_at",
          "type": "integer",
          "primaryKey": false,
          "notNull": true,
          "autoincrement": false
        }
      },
      "indexes": {
        "idx_tasks_chat_id": {
          "name": "idx_tasks_chat_id",
          "columns": ["chat_id"],
          "isUnique": false
        },
        "idx_tasks_status": {
          "name": "idx_tasks_status",
          "columns": ["status"],
          "isUnique": false
        },
        "idx_tasks_claimed_by": {
          "name": "idx_tasks_claimed_by",
          "columns": ["claimed_by"],
          "isUnique": false
        }
      },
      "foreignKeys": {
        "tasks_chat_id_chats_id_fk": {
          "name": "tasks_chat_id_chats_id_fk",
          "tableFrom": "tasks",
          "tableTo": "chats",
          "columnsFrom": ["chat_id"],
          "columnsTo": ["id"],
          "onDelete": "cascade",
          "onUpdate": "no action"
        }
      },
      "compositePrimaryKeys": {},
      "uniqueConstraints": {},
      "checkConstraints": {}
    },
    "workspaces": {
      "name": "workspaces",
      "columns": {
        "id": {
          "name": "id",
          "type": "text",
          "primaryKey": true,
          "notNull": true,
          "autoincrement": false
        },
        "project_id": {
          "name": "project_id",
          "type": "text",
          "primaryKey": false,
          "notNull": true,
          "autoincrement": false
        },
        "path": {
          "name": "path",
          "type": "text",
          "primaryKey": false,
          "notNull": true,
          "autoincrement": false
        },
        "branch": {
          "name": "branch",
          "type": "text",
          "primaryKey": false,
          "notNull": true,
          "autoincrement": false
        },
        "name": {
          "name": "name",
          "type": "text",
          "primaryKey": false,
          "notNull": true,
          "autoincrement": false
        },
        "status": {
          "name": "status",
          "type": "text",
          "primaryKey": false,
          "notNull": true,
          "autoincrement": false,
          "default": "'active'"
        },
        "created_at": {
          "name": "created_at",
          "type": "integer",
          "primaryKey": false,
          "notNull": true,
          "autoincrement": false
        },
        "last_accessed_at": {
          "name": "last_accessed_at",
          "type": "integer",
          "primaryKey": false,
          "notNull": true,
          "autoincrement": false
        }
      },
      "indexes": {
        "workspaces_path_unique": {
          "name": "workspaces_path_unique",
          "columns": ["path"],
          "isUnique": true
        },
        "idx_workspaces_project_id": {
          "name": "idx_workspaces_project_id",
          "columns": ["project_id"],
          "isUnique": false
        },
        "idx_workspaces_status": {
          "name": "idx_workspaces_status",
          "columns": ["status"],
          "isUnique": false
        },
        "idx_workspaces_last_accessed": {
          "name": "idx_workspaces_last_accessed",
          "columns": ["last_accessed_at"],
          "isUnique": false
        }
      },
      "foreignKeys": {
        "workspaces_project_id_projects_id_fk": {
          "name": "workspaces_project_id_projects_id_fk",
          "tableFrom": "workspaces",
          "tableTo": "projects",
          "columnsFrom": ["project_id"],
          "columnsTo": ["id"],
          "onDelete": "cascade",
          "onUpdate": "no action"
        }
      },
      "compositePrimaryKeys": {},
      "uniqueConstraints": {},
      "checkConstraints": {}
    }
  },
  "views": {},
  "enums": {},
  "_meta": {
    "schemas": {},
    "tables": {},
    "columns": {}
  },
  "internal": {
    "indexes": {}
  }
}
